builder.py
zaml.cpython-36m-x86_64-linux-gnu.so
zaml-0.0.9.dist-info/LICENSE
zaml-0.0.9.dist-info/top_level.txt
zaml-0.0.9.dist-info/WHEEL
zaml-0.0.9.dist-info/METADATA
zaml-0.0.9.dist-info/RECORD
