Metadata-Version: 2.1
Name: zaml
Version: 0.0.9
Summary: Fast YAML 1.2 Parser for Python 3.6+
Home-page: https://github.com/adamserafini/zaml
License-File: LICENSE
